deepsights/__init__.py
deepsights/_version.py
deepsights/exceptions.py
deepsights/api/__init__.py
deepsights/api/api.py
deepsights/api/resource.py
deepsights/api/unified_token.py
deepsights/contentstore/__init__.py
deepsights/contentstore/contentstore.py
deepsights/contentstore/resources/__init__.py
deepsights/contentstore/resources/_download.py
deepsights/contentstore/resources/_model.py
deepsights/contentstore/resources/_search.py
deepsights/contentstore/resources/_url.py
deepsights/contentstore/resources/news.py
deepsights/contentstore/resources/secondary.py
deepsights/deepsights/__init__.py
deepsights/deepsights/_mip_identity.py
deepsights/deepsights/deepsights.py
deepsights/deepsights/resources/__init__.py
deepsights/deepsights/resources/quota/__init__.py
deepsights/deepsights/resources/quota/_model.py
deepsights/deepsights/resources/quota/quota.py
deepsights/documentstore/__init__.py
deepsights/documentstore/documentstore.py
deepsights/documentstore/resources/__init__.py
deepsights/documentstore/resources/documents/__init__.py
deepsights/documentstore/resources/documents/_cache.py
deepsights/documentstore/resources/documents/_delete.py
deepsights/documentstore/resources/documents/_download.py
deepsights/documentstore/resources/documents/_list.py
deepsights/documentstore/resources/documents/_load.py
deepsights/documentstore/resources/documents/_model.py
deepsights/documentstore/resources/documents/_search.py
deepsights/documentstore/resources/documents/_segmenter.py
deepsights/documentstore/resources/documents/_taxonomy.py
deepsights/documentstore/resources/documents/_upload.py
deepsights/documentstore/resources/documents/documents.py
deepsights/documentstore/resources/taxonomies/__init__.py
deepsights/documentstore/resources/taxonomies/_model.py
deepsights/documentstore/resources/taxonomies/_taxon_crud.py
deepsights/documentstore/resources/taxonomies/_taxon_type_crud.py
deepsights/documentstore/resources/taxonomies/_taxonomy_crud.py
deepsights_api-1.7.0.dist-info/METADATA
deepsights_api-1.7.0.dist-info/WHEEL
deepsights_api-1.7.0.dist-info/licenses/LICENSE
deepsights_api-1.7.0.dist-info/RECORD
