Metadata-Version: 2.4
Name: deepsights-api
Version: 1.7.0
Summary: Python library for the DeepSights APIs
Project-URL: Documentation, https://marketlogicsoftware.github.io/deepsights-api/
Project-URL: Repository, https://github.com/marketlogicsoftware/deepsights-api
Author-email: Market Logic Software <info@marketlogicsoftware.com>
License: Apache-2.0
License-File: LICENSE
Classifier: Intended Audience :: Developers
Classifier: License :: OSI Approved :: Apache Software License
Classifier: Programming Language :: Python :: 3.10
Classifier: Programming Language :: Python :: 3.11
Classifier: Programming Language :: Python :: 3.12
Requires-Python: >=3.10
Requires-Dist: cachetools>=5.3.1
Requires-Dist: pydantic>=2.6.1
Requires-Dist: ratelimit>=2.2.1
Requires-Dist: requests>=2.31.0
Requires-Dist: tenacity>=8.2.3
Requires-Dist: types-cachetools>=6.2.0.20251022
Provides-Extra: docs
Requires-Dist: pdoc>=14.4.0; extra == 'docs'
Provides-Extra: lint
Requires-Dist: mypy>=1.10.0; extra == 'lint'
Requires-Dist: pre-commit>=3.7.0; extra == 'lint'
Requires-Dist: ruff>=0.6.9; extra == 'lint'
Requires-Dist: types-cachetools>=5.3.0; extra == 'lint'
Requires-Dist: types-requests>=2.31.0.20240218; extra == 'lint'
Provides-Extra: test
Requires-Dist: pytest>=8.0.2; extra == 'test'
Requires-Dist: python-dotenv>=1.0.1; extra == 'test'
